persona/__init__.py
persona-0.0.1.dist-info/LICENSE
persona-0.0.1.dist-info/METADATA
persona-0.0.1.dist-info/WHEEL
persona-0.0.1.dist-info/top_level.txt
persona-0.0.1.dist-info/RECORD
