Metadata-Version: 2.1
Name: persona
Version: 0.0.1
Summary: A package to help in writing a novel.
Home-page: https://github.com/pypa/sampleproject
Author: Criss Davis
Author-email: criss.ej.davis@gmail.com
License: UNKNOWN
Platform: UNKNOWN
Classifier: Programming Language :: Python :: 3
Classifier: License :: OSI Approved :: MIT License
Classifier: Operating System :: OS Independent
Requires-Python: >=3.6
